odoo9_addon_payment_redsys-9.0.1.0.0.99.dev9-py2.7-nspkg.pth
odoo9_addon_payment_redsys-9.0.1.0.0.99.dev9.dist-info/DESCRIPTION.rst
odoo9_addon_payment_redsys-9.0.1.0.0.99.dev9.dist-info/METADATA
odoo9_addon_payment_redsys-9.0.1.0.0.99.dev9.dist-info/RECORD
odoo9_addon_payment_redsys-9.0.1.0.0.99.dev9.dist-info/WHEEL
odoo9_addon_payment_redsys-9.0.1.0.0.99.dev9.dist-info/metadata.json
odoo9_addon_payment_redsys-9.0.1.0.0.99.dev9.dist-info/namespace_packages.txt
odoo9_addon_payment_redsys-9.0.1.0.0.99.dev9.dist-info/top_level.txt
odoo_addons/payment_redsys/README.rst
odoo_addons/payment_redsys/__init__.py
odoo_addons/payment_redsys/__openerp__.py
odoo_addons/payment_redsys/controllers/__init__.py
odoo_addons/payment_redsys/controllers/main.py
odoo_addons/payment_redsys/data/payment_redsys.xml
odoo_addons/payment_redsys/i18n/bg.po
odoo_addons/payment_redsys/i18n/ca.po
odoo_addons/payment_redsys/i18n/es.po
odoo_addons/payment_redsys/i18n/eu.po
odoo_addons/payment_redsys/i18n/fr.po
odoo_addons/payment_redsys/i18n/gl.po
odoo_addons/payment_redsys/i18n/hr.po
odoo_addons/payment_redsys/i18n/payment_redsys.pot
odoo_addons/payment_redsys/i18n/pt_BR.po
odoo_addons/payment_redsys/i18n/sl.po
odoo_addons/payment_redsys/models/__init__.py
odoo_addons/payment_redsys/models/redsys.py
odoo_addons/payment_redsys/static/description/icon.png
odoo_addons/payment_redsys/static/src/img/redsys_icon.png
odoo_addons/payment_redsys/tests/__init__.py
odoo_addons/payment_redsys/tests/test_redsys.py
odoo_addons/payment_redsys/views/payment_acquirer.xml
odoo_addons/payment_redsys/views/redsys.xml
